geneuler/__init__.py
geneuler/fem.py
geneuler/mesh.py
geneuler-0.2.1.dist-info/METADATA
geneuler-0.2.1.dist-info/WHEEL
geneuler-0.2.1.dist-info/licenses/LICENSE
geneuler-0.2.1.dist-info/RECORD
