Metadata-Version: 2.4
Name: geneuler
Version: 0.2.1
Summary: Lightweight mesh generation and I/O (Gmsh+meshio) for GenEuler.
Project-URL: Homepage, https://github.com/your-org/geneuler
Project-URL: Issues, https://github.com/your-org/geneuler/issues
Author-email: Mohamad Kokh <mohamad.kokh@gmail.com>
License: MIT License
License-File: LICENSE
Keywords: gmsh,mesh,step,stl,tetrahedral,xdmf
Classifier: Development Status :: 3 - Alpha
Classifier: Intended Audience :: Science/Research
Classifier: License :: OSI Approved :: MIT License
Classifier: Programming Language :: Python :: 3
Classifier: Programming Language :: Python :: 3 :: Only
Classifier: Programming Language :: Python :: 3.9
Classifier: Programming Language :: Python :: 3.10
Classifier: Programming Language :: Python :: 3.11
Classifier: Programming Language :: Python :: 3.12
Classifier: Topic :: Scientific/Engineering
Requires-Python: >=3.9
Requires-Dist: gmsh
Requires-Dist: meshio
Requires-Dist: numpy
Requires-Dist: pyamg
Requires-Dist: scikit-fem
Requires-Dist: scipy
